{
  "schemaVersion": 1,
  "id": "magnetizing",
  "version": "${version}",
  "name": "Magnetizing",
  "description": "Adds items and blocks based around magnets",
  "authors": [
    "Command17"
  ],
  "contact": {
    "homepage": "https://modrinth.com/mod/magnetizing",
    "issues": "https://github.com/Command17/Magnetizing"
  },
  "license": "MIT",
  "icon": "assets/magnetizing/icon.png",
  "environment": "*",
  "entrypoints": {
    "main": [
      "com.github.command17.magnetizing.fabric.MagnetizingFabric"
    ],
    "fabric-datagen": [
      "com.github.command17.magnetizing.fabric.data.MagnetizingDataGen"
    ]
  },
  "mixins": [
    "magnetizing.mixins.json"
  ],
  "depends": {
    "fabricloader": ">=0.18.1",
    "minecraft": "~1.21.1",
    "java": ">=21",
    "architectury": ">=13.0.8",
    "forgeconfigapiport": ">=21.1.3",
    "fabric-api": "*"
  },
  "suggests": {
    "another-mod": "*"
  },
  "custom": {
    "modmenu": {
      "links": {
        "modmenu.source": "https://github.com/Command17/Magnetizing"
      }
    }
  }
}
